pushdata/__init__.py
pushdata/pushdata.py
pushdata_io-0.1.0.dist-info/LICENSE
pushdata_io-0.1.0.dist-info/METADATA
pushdata_io-0.1.0.dist-info/WHEEL
pushdata_io-0.1.0.dist-info/top_level.txt
pushdata_io-0.1.0.dist-info/RECORD
