Metadata-Version: 2.1
Name: pushdata-io
Version: 0.1.0
Summary: Python client library for pushdata.io
Home-page: https://github.com/pushdata-io/Python
Author: Ragnar Lonn
Author-email: hello@pushdata.io
License: UNKNOWN
Platform: UNKNOWN
Classifier: Programming Language :: Python :: 2
Classifier: Programming Language :: Python :: 3
Classifier: License :: OSI Approved :: MIT License
Classifier: Operating System :: OS Independent
Requires-Dist: requests
